[
  {
    "inputs": [
      {
        "internalType": "address",
        "name": "addr",
        "type": "address"
      }
    ],
    "name": "fromAddressHexFixed",
    "outputs": [
      {
        "internalType": "string",
        "name": "",
        "type": "string"
      }
    ],
    "stateMutability": "pure",
    "type": "function"
  },
  {
    "inputs": [
      {
        "internalType": "uint256",
        "name": "value",
        "type": "uint256"
      }
    ],
    "name": "fromUint256",
    "outputs": [
      {
        "internalType": "string",
        "name": "",
        "type": "string"
      }
    ],
    "stateMutability": "pure",
    "type": "function"
  },
  {
    "inputs": [
      {
        "internalType": "uint256",
        "name": "value",
        "type": "uint256"
      }
    ],
    "name": "fromUint256Hex",
    "outputs": [
      {
        "internalType": "string",
        "name": "",
        "type": "string"
      }
    ],
    "stateMutability": "pure",
    "type": "function"
  },
  {
    "inputs": [
      {
        "internalType": "uint256",
        "name": "value",
        "type": "uint256"
      },
      {
        "internalType": "uint256",
        "name": "length",
        "type": "uint256"
      }
    ],
    "name": "fromUint256HexFixed",
    "outputs": [
      {
        "internalType": "string",
        "name": "",
        "type": "string"
      }
    ],
    "stateMutability": "pure",
    "type": "function"
  }
]
